{
  "questions": [
    {
      "category": "conhecimentos gerais",
      "hook": "Essa parece facil, mas muita gente erra",
      "question": "Qual e o maior oceano do planeta?",
      "options": ["Atlantico", "Indico", "Pacifico", "Artico"],
      "correct_index": 2,
      "explanation": "O Oceano Pacifico e o maior do planeta.",
      "difficulty": "facil"
    },
    {
      "category": "geografia",
      "hook": "Voce acerta essa sem olhar no mapa?",
      "question": "Qual e a capital do Canada?",
      "options": ["Toronto", "Ottawa", "Vancouver", "Montreal"],
      "correct_index": 1,
      "explanation": "A capital do Canada e Ottawa.",
      "difficulty": "medio"
    },
    {
      "category": "historia",
      "hook": "So quem prestou atencao na escola lembra",
      "question": "Em que ano o Brasil proclamou a independencia?",
      "options": ["1500", "1808", "1822", "1889"],
      "correct_index": 2,
      "explanation": "A independencia do Brasil foi proclamada em 1822.",
      "difficulty": "facil"
    },
    {
      "category": "ciencia",
      "hook": "Pergunta rapida de ciencia",
      "question": "Qual gas as plantas absorvem na fotossintese?",
      "options": ["Oxigenio", "Nitrogenio", "Gas carbonico", "Helio"],
      "correct_index": 2,
      "explanation": "As plantas absorvem gas carbonico na fotossintese.",
      "difficulty": "facil"
    },
    {
      "category": "filmes",
      "hook": "Cinefilo de verdade acerta",
      "question": "Quem dirigiu o filme Titanic de 1997?",
      "options": ["James Cameron", "Steven Spielberg", "Christopher Nolan", "George Lucas"],
      "correct_index": 0,
      "explanation": "Titanic foi dirigido por James Cameron.",
      "difficulty": "medio"
    },
    {
      "category": "futebol",
      "hook": "Torcedor raiz acerta rapido",
      "question": "Qual pais venceu a Copa do Mundo de 2002?",
      "options": ["Alemanha", "Brasil", "Franca", "Argentina"],
      "correct_index": 1,
      "explanation": "O Brasil venceu a Copa do Mundo de 2002.",
      "difficulty": "facil"
    },
    {
      "category": "paises",
      "hook": "Voce conhece as capitais do mundo?",
      "question": "Qual pais tem Buenos Aires como capital?",
      "options": ["Chile", "Uruguai", "Argentina", "Paraguai"],
      "correct_index": 2,
      "explanation": "Buenos Aires e a capital da Argentina.",
      "difficulty": "facil"
    },
    {
      "category": "bandeiras",
      "hook": "Desafio de bandeiras em 5 segundos",
      "question": "Qual cor NAO aparece na bandeira do Brasil?",
      "options": ["Verde", "Amarelo", "Azul", "Vermelho"],
      "correct_index": 3,
      "explanation": "A bandeira do Brasil nao tem vermelho.",
      "difficulty": "facil"
    },
    {
      "category": "matematica rapida",
      "hook": "Sem calculadora, responde agora",
      "question": "Quanto e 12 x 12?",
      "options": ["124", "132", "144", "156"],
      "correct_index": 2,
      "explanation": "12 vezes 12 e 144.",
      "difficulty": "facil"
    },
    {
      "category": "90% erram",
      "hook": "90% erram essa por responder rapido",
      "question": "Quantos meses tem 28 dias?",
      "options": ["1", "2", "12", "Depende do ano"],
      "correct_index": 2,
      "explanation": "Todos os 12 meses tem pelo menos 28 dias.",
      "difficulty": "medio"
    },
    {
      "category": "so genios acertam",
      "hook": "So genios acertam sem pausar",
      "question": "Qual numero completa a sequencia: 2, 4, 8, 16, ?",
      "options": ["20", "24", "30", "32"],
      "correct_index": 3,
      "explanation": "A sequencia dobra a cada passo, entao o proximo numero e 32.",
      "difficulty": "facil"
    },
    {
      "category": "voce consegue",
      "hook": "Voce consegue acertar antes do tempo acabar?",
      "question": "Qual destes e um numero primo?",
      "options": ["21", "27", "29", "33"],
      "correct_index": 2,
      "explanation": "29 e primo porque so e divisivel por 1 e por 29.",
      "difficulty": "medio"
    }
  ]
}
